rhvoice_wrapper_data/__init__.py
rhvoice_wrapper_data/data/languages/Albanian/accented.dt
rhvoice_wrapper_data/data/languages/Albanian/downcase.fst
rhvoice_wrapper_data/data/languages/Albanian/dur-mod.dt
rhvoice_wrapper_data/data/languages/Albanian/emoji.fst
rhvoice_wrapper_data/data/languages/Albanian/g2p.fst
rhvoice_wrapper_data/data/languages/Albanian/gpos.fst
rhvoice_wrapper_data/data/languages/Albanian/graph.txt
rhvoice_wrapper_data/data/languages/Albanian/key.fst
rhvoice_wrapper_data/data/languages/Albanian/labelling.xml
rhvoice_wrapper_data/data/languages/Albanian/language.conf
rhvoice_wrapper_data/data/languages/Albanian/language.info
rhvoice_wrapper_data/data/languages/Albanian/locale.info
rhvoice_wrapper_data/data/languages/Albanian/lseq.fst
rhvoice_wrapper_data/data/languages/Albanian/msg.fst
rhvoice_wrapper_data/data/languages/Albanian/numbers.fst
rhvoice_wrapper_data/data/languages/Albanian/pg2p.fst
rhvoice_wrapper_data/data/languages/Albanian/phonemes.xml
rhvoice_wrapper_data/data/languages/Albanian/phrasing.dt
rhvoice_wrapper_data/data/languages/Albanian/pitch-mod.dt
rhvoice_wrapper_data/data/languages/Albanian/qst.fst
rhvoice_wrapper_data/data/languages/Albanian/spell.fst
rhvoice_wrapper_data/data/languages/Albanian/syl.fst
rhvoice_wrapper_data/data/languages/Albanian/tok.fst
rhvoice_wrapper_data/data/languages/Brazilian-Portuguese/downcase.fst
rhvoice_wrapper_data/data/languages/Brazilian-Portuguese/dur-mod.dt
rhvoice_wrapper_data/data/languages/Brazilian-Portuguese/emoji.fst
rhvoice_wrapper_data/data/languages/Brazilian-Portuguese/g2p.fst
rhvoice_wrapper_data/data/languages/Brazilian-Portuguese/gpos.fst
rhvoice_wrapper_data/data/languages/Brazilian-Portuguese/homographs.fst
rhvoice_wrapper_data/data/languages/Brazilian-Portuguese/key.fst
rhvoice_wrapper_data/data/languages/Brazilian-Portuguese/labelling.xml
rhvoice_wrapper_data/data/languages/Brazilian-Portuguese/language.info
rhvoice_wrapper_data/data/languages/Brazilian-Portuguese/lseq.fst
rhvoice_wrapper_data-0.5.0.dist-info/LICENSE.md
rhvoice_wrapper_data-0.5.0.dist-info/METADATA
rhvoice_wrapper_data-0.5.0.dist-info/WHEEL
rhvoice_wrapper_data-0.5.0.dist-info/top_level.txt
rhvoice_wrapper_data-0.5.0.dist-info/RECORD
