Metadata-Version: 2.1
Name: rhvoice-wrapper-data
Version: 0.5.0
Summary: Provides RHVoice data for rhvoice-wrapper-bin
Home-page: https://github.com/Aculeasis/rhvoice-wrapper-data
Author: Aculeasis
Author-email: amilpalimov2@ya.ru
License: GPLv3+
Classifier: Intended Audience :: Developers
Classifier: Programming Language :: Python :: 3
Classifier: License :: OSI Approved :: GNU General Public License v3 or later (GPLv3+)
Classifier: Operating System :: OS Independent
Classifier: Topic :: Multimedia :: Sound/Audio :: Speech
Requires-Python: >=3.4
License-File: LICENSE.md
